[
    { "id": 123753250, "name": "Back On Keanan", "demon_type": 4, "rate": "epic", "ptsBeat": 7 },
    { "id": 139945056, "name": "Can't Let Kean", "demon_type": 6, "rate": "mythic", "ptsBeat": 30 },
    { "id": 131279920, "name": "Caput Keanandi", "demon_type": 5, "rate": "mythic", "ptsBeat": 14 },
    { "id": 132471191, "name": "ElectroKeanan", "demon_type": 6, "rate": "feature", "ptsBeat": 20 },
    { "id": 134524819, "name": "Empyrkean", "demon_type": 6, "rate": "mythic", "ptsBeat": 17 },
    { "id": 136328329, "name": "GREEN KEANAN", "demon_type": 4, "rate": "featured", "ptsBeat": 8 },
    { "id": 132280763, "name": "How Keanan Works", "demon_type": 5, "rate": "mythic", "ptsBeat": 14 },
    { "id": 131711366, "name": "Kash", "demon_type": 5, "rate": "featured", "ptsBeat": 13 },
    { "id": 136629316, "name": "Kash Full Version", "demon_type": 6, "rate": "legendary", "ptsBeat": 15 },
    { "id": 132393059, "name": "KeaDuck V0rtr0x", "demon_type": 6, "rate": "mythic", "ptsBeat": 20 },
    { "id": 139826641, "name": "KeaNaLiXZCliH", "demon_type": 5, "rate": "featured", "ptsBeat": 13 },
    { "id": 123646486, "name": "Keanan00 Dominator", "demon_type": 6, "rate": "epic", "ptsBeat": 17 },
    { "id": 123646349, "name": "Keanan00 Polargeist", "demon_type": 5, "rate": "epic", "ptsBeat": 10 },
    { "id": 123646466, "name": "Keanan CLutterfunk", "demon_type": 6, "rate": "epic", "ptsBeat": 15 },
    { "id": 137606675, "name": "Keanan Calamity", "demon_type": 6, "rate": "legendary", "ptsBeat": 30 },
    { "id": 139306629, "name": "Keanan Corridor II", "demon_type": 3, "rate": "featured", "ptsBeat": 1 },
    { "id": 137480998, "name": "Keanan Decay's..", "demon_type": 4, "rate": "epic", "ptsBeat": 7 },
    { "id": 139363950, "name": "Keanan Dried Mango", "demon_type": 4, "rate": "featured", "ptsBeat": 8 },
    { "id": 132532863, "name": "Keanan Drop", "demon_type": 6, "rate": "legendary", "ptsBeat": 30 },
    { "id": 138783706, "name": "Keanan Fire Head", "demon_type": 6, "rate": "mythic", "ptsBeat": 17 },
    { "id": 129517724, "name": "Keanan Gets Fingered", "demon_type": 6, "rate": "legendary", "ptsBeat": 17 },
    { "id": 125560947, "name": "Keanan Goes Explorin'", "demon_type": 6, "rate": "epic", "ptsBeat": 30 },
    { "id": 139876612, "name": "Keanan Got Talent", "demon_type": 6, "rate": "legendary", "ptsBeat": 30 },
    { "id": 139826026, "name": "Keanan Is Angry", "demon_type": 6, "rate": "legendary", "ptsBeat": 15 },
    { "id": 131277954, "name": "Keanan Is Based", "demon_type": 6, "rate": "legendary", "ptsBeat": 15 },
    { "id": 128546764, "name": "Keanan Is Bouncy UwU", "demon_type": 6, "rate": "epic", "ptsBeat": 17 },
    { "id": 130338213, "name": "Keanan Is Dry", "demon_type": 6, "rate": "epic", "ptsBeat": 17 },
    { "id": 123979138, "name": "Keanan Is Locked In", "demon_type": 6, "rate": "epic", "ptsBeat": 17 },
    { "id": 137226785, "name": "Keanan Is Morphed", "demon_type": 6, "rate": "legendary", "ptsBeat": 17 },
    { "id": 130337633, "name": "Keaann Is In HeLL",  "demon_type": 6, "rate": "legandary", "ptsBeat": 17 },
    { "id": 136877416, "name": "Keanan Is Nocked' Up", "demon_type": 5, "rate": "mythic", "ptsBeat": 10 },
    { "id": 129317413, "name": "Keanan Is Racist", "demon_type": 6, "rate": "mythic", "ptsBeat": 30 },
    { "id": 135241711, "name": "Keanan Is Ron", "demon_type": 5, "rate": "mythic", "ptsBeat": 8 },
    { "id": 132529740, "name": "Keanan Is Special", "demon_type": 5, "rate": "legendary", "ptsBeat": 14 },
    { "id": 136624345, "name": "KEANAN IS WET", "demon_type": 6, "rate": "rated", "ptsBeat": 17 },
    { "id": 134773859, "name": "Keanan Loves Fun!", "demon_type": 4, "rate": "legendary", "ptsBeat": 8 },
    { "id": 133678715, "name": "Keanan Machine", "demon_type": 6, "rate": "mythic", "ptsBeat": 20 },
    { "id": 129646769, "name": "Keanan No Force", "demon_type": 5, "rate": "featured", "ptsBeat": 14 },
    { "id": 137735286, "name": "Keanan Pirate Raid", "demon_type": 3, "rate": "epic", "ptsBeat": 1 },
    { "id": 135904450, "name": "Keanan Ship Trials", "demon_type": 5, "rate": "legendary", "ptsBeat": 14 },
    { "id": 138535611, "name": "Keanan Silhouette", "demon_type": 6, "rate": "epic", "ptsBeat": 15 },
    { "id": 135788052, "name": "Keanan Spaced Out", "demon_type": 6, "rate": "mythic", "ptsBeat": 15 },
    { "id": 134973634, "name": "Keanan Wave Trials", "demon_type": 6, "rate": "mythic", "ptsBeat": 17 },
    { "id": 133102844, "name": "Keanan X Steps Up", "demon_type": 4, "rate": "legendary", "ptsBeat": 8 },
    { "id": 133763783, "name": "Keanan's Bloodline", "demon_type": 5, "rate": "mythic", "ptsBeat": 10 },
    { "id": 137795293, "name": "Keanan's Breaking Point", "demon_type": 6, "rate": "mythic", "ptsBeat": 17 },
    { "id": 130058295, "name": "Keanan's Clubtrap", "demon_type": 4, "rate": "epic", "ptsBeat": 2 },
    { "id": 129279251, "name": "Keanan's End Adventure", "demon_type": 6, "rate": "feature", "ptsBeat": 20 },
    { "id": 129707565, "name": "Keanan's Final Straw", "demon_type": 6, "rate": "epic", "ptsBeat": 30 },
    { "id": 135358299, "name": "Keanan's Hell", "demon_type": 5, "rate": "featured", "ptsBeat": 8 },
    { "id": 136912493, "name": "Keanan's Jawline", "demon_type": 6, "rate": "epic", "ptsBeat": 17 },
    { "id": 135165984, "name": "KeananIsLowkShivering", "demon_type": 6, "rate": "mythic", "ptsBeat": 30 },
    { "id": 123753221, "name": "Keananmare", "demon_type": 6, "rate": "epic", "ptsBeat": 14 },
    { "id": 138855442, "name": "Kean Isn't Denouement", "demon_type": 6, "rate": "featured", "ptsBeat": 17 },
    { "id": 137823670, "name": "Keanifestation", "demon_type": 6, "rate": "legendary", "ptsBeat": 15 },
    { "id": 133600508, "name": "KeAtRaY", "demon_type": 5, "rate": "epic", "ptsBeat": 14 },
    { "id": 137663424, "name": "Kears", "demon_type": 3, "rate": "featured", "ptsBeat": 1 },
    { "id": 138784079, "name": "Kilh0uette0 Karden0", "demon_type": 6, "rate": "legendary", "ptsBeat": 20 },
    { "id": 133884478, "name": "KRUSH", "demon_type": 5, "rate": "legendary", "ptsBeat": 14 },
    { "id": 123646390, "name": "Krenono Buffed", "demon_type": 4, "rate": "rated", "ptsBeat": 7 },
    { "id": 123646413, "name": "Krenono Buffed Buffed", "demon_type": 6, "rate": "featured", "ptsBeat": 15 },
    { "id": 130250431, "name": "Krenono Tripple Buff", "demon_type": 6, "rate": "epic", "ptsBeat": 17 },
    { "id": 139235927, "name": "Kycles", "demon_type": 6, "rate": "epic", "ptsBeat": 17 },
    { "id": 139515564, "name": "La Kkeana", "demon_type": 6, "rate": "legendary", "ptsBeat": 17 },
    { "id": 135638375, "name": "Nine Keys", "demon_type": 6, "rate": "legendary", "ptsBeat": 30 },
    { "id": 136059228, "name": "Press Keanan!", "demon_type": 5, "rate": "mythic", "ptsBeat": 7 },
    { "id": 135106600, "name": "Sakupen Keanan", "demon_type": 5, "rate": "featured", "ptsBeat": 14 },
    { "id": 135762615, "name": "Shardskapes", "demon_type": 5, "rate": "epic", "ptsBeat": 14 },
    { "id": 139527996, "name": "Supersonic Keanan", "demon_type": 6, "rate": "featured", "ptsBeat": 7 },
    { "id": 133149552, "name": "The Party In Keany", "demon_type": 3, "rate": "legendary", "ptsBeat": 1 },
    { "id": 134617748, "name": "You've Been Keanan'd", "demon_type": 4, "rate": "featured", "ptsBeat": 6 }
]
